README.md
setup.cfg
setup.py
distributions/Binomialdistribution.py
distributions/Gaussiandistribution.py
distributions/Generaldistribution.py
distributions/__init__.py
stcs_distributions.egg-info/PKG-INFO
stcs_distributions.egg-info/SOURCES.txt
stcs_distributions.egg-info/dependency_links.txt
stcs_distributions.egg-info/not-zip-safe
stcs_distributions.egg-info/top_level.txt